filtered_flask/__init__.py
filtered_flask/app.py
filtered_flask-0.1.0.dist-info/METADATA
filtered_flask-0.1.0.dist-info/WHEEL
filtered_flask-0.1.0.dist-info/top_level.txt
filtered_flask-0.1.0.dist-info/RECORD
