Metadata-Version: 2.1
Name: filtered-flask
Version: 0.1.0
Classifier: Programming Language :: Python :: 3
Requires-Dist: Flask
